{
    "description": "This straightforward hotel housed in a brick building is 14 km from the Bangabandhu Sheikh Mujib Safari Park, and 13 km from the picnic area at Nuhash Polli.",
    "external_url": "https://www.bhawalresort.com",
    "image": "ipfs://QmWs12BtB4wsujne1pyRkCPpyefYzsHggUX8TPca8iDrdF",
    "name": "The Royena Resort Ltd",
    "attributes": [
        {
            "phone": "01332-830000"
        },
        {
            "location": "Vannara bazar, Mouchak - Fulbaria Rd, Kaliakair 1750"
        },
        {
            "stars": 3
        }
    ]
}